{
  "market_id": "0xPMKT123456789",
  "spread_history": [
    { "timestamp": 1738748400, "best_bid": 0.487, "best_ask": 0.501, "spread": 0.014 },
    { "timestamp": 1738749000, "best_bid": 0.488, "best_ask": 0.500, "spread": 0.012 },
    { "timestamp": 1738749600, "best_bid": 0.490, "best_ask": 0.502, "spread": 0.012 },
    { "timestamp": 1738750200, "best_bid": 0.489, "best_ask": 0.500, "spread": 0.011 },
    { "timestamp": 1738750800, "best_bid": 0.491, "best_ask": 0.499, "spread": 0.008 },
    { "timestamp": 1738751400, "best_bid": 0.485, "best_ask": 0.499, "spread": 0.014 },
    { "timestamp": 1738752000, "best_bid": 0.485, "best_ask": 0.499, "spread": 0.014 }
  ],
  "metadata": {
    "interval": "10m",
    "points": 7
  }
}
